llm_templates_sourcehut.py
llm_templates_sourcehut-0.1.dist-info/licenses/LICENSE
llm_templates_sourcehut-0.1.dist-info/METADATA
llm_templates_sourcehut-0.1.dist-info/WHEEL
llm_templates_sourcehut-0.1.dist-info/entry_points.txt
llm_templates_sourcehut-0.1.dist-info/top_level.txt
llm_templates_sourcehut-0.1.dist-info/RECORD
