Metadata-Version: 2.4
Name: llm-templates-sourcehut
Version: 0.1
Summary: Load LLM templates from SourceHut repositories
Author: Amolith
License: Apache-2.0
Project-URL: Homepage, https://git.sr.ht/~amolith/llm-templates-sourcehut
Project-URL: Changelog, https://git.sr.ht/~amolith/llm-templates-sourcehut/refs
Project-URL: Issues, https://todo.sr.ht/~amolith/public-tracker
Classifier: License :: OSI Approved :: Apache Software License
Requires-Python: >=3.9
License-File: LICENSE
Requires-Dist: llm>=0.24
Provides-Extra: test
Requires-Dist: pytest; extra == "test"
Requires-Dist: pytest-httpx; extra == "test"
Dynamic: license-file
